vizcode/LICENSE.txt
vizcode/__init__.py
vizcode/command_line.py
vizcode/constants.py
vizcode/data.db
vizcode/db.py
vizcode/frontend/build/android-chrome-192x192.png
vizcode/frontend/build/android-chrome-512x512.png
vizcode/frontend/build/apple-touch-icon.png
vizcode/frontend/build/asset-manifest.json
vizcode/frontend/build/code/.gitkeep
vizcode/frontend/build/code/python/.gitkeep
vizcode/frontend/build/code/python/main/.gitkeep
vizcode/frontend/build/code/python/main/edge-code/.gitkeep
vizcode/frontend/build/code/python/main/node-code/.gitkeep
vizcode/frontend/build/company-icon.png
vizcode/frontend/build/favicon-16x16.png
vizcode/frontend/build/favicon-32x32.png
vizcode/frontend/build/favicon.ico
vizcode/frontend/build/index.html
vizcode/frontend/build/manifest.json
vizcode/frontend/build/robots.txt
vizcode/frontend/build/static/css/main.6dea0f05.chunk.css
vizcode/frontend/build/static/css/main.6dea0f05.chunk.css.map
vizcode/frontend/build/static/js/2.30bdde92.chunk.js
vizcode/frontend/build/static/js/2.30bdde92.chunk.js.LICENSE.txt
vizcode/frontend/build/static/js/2.30bdde92.chunk.js.map
vizcode/frontend/build/static/js/3.de4c2f6a.chunk.js
vizcode/frontend/build/static/js/3.de4c2f6a.chunk.js.map
vizcode/frontend/build/static/js/main.9456c86a.chunk.js
vizcode/frontend/build/static/js/main.9456c86a.chunk.js.map
vizcode/frontend/build/static/js/runtime-main.525df6ee.js
vizcode/frontend/build/static/js/runtime-main.525df6ee.js.map
vizcode/graph.py
vizcode/helpers.py
vizcode/indexer.py
vizcode/main.py
vizcode/parsing.py
vizcode/scripts.py
vizcode-0.4.1.dist-info/entry_points.txt
vizcode-0.4.1.dist-info/WHEEL
vizcode-0.4.1.dist-info/METADATA
vizcode-0.4.1.dist-info/RECORD
