Metadata-Version: 2.1
Name: vizcode
Version: 0.4.1
Summary: Create a dependency graph of your codebase
Home-page: https://vizcode.dev
License: GPL Public License
Keywords: code visualization,static analysis,debugging
Author: Alex Rubin, Maciej Holubiec, Karthik Rao
Requires-Python: >=3.7,<4.0
Classifier: License :: Other/Proprietary License
Classifier: Programming Language :: Python :: 3
Classifier: Programming Language :: Python :: 3.7
Classifier: Programming Language :: Python :: 3.8
Classifier: Programming Language :: Python :: 3.9
Classifier: Topic :: Software Development
Requires-Dist: art (>=5.1,<6.0)
Requires-Dist: jedi (>=0.17.2,<0.18.0)
Requires-Dist: parso (>=0.7.0,<0.8.0)
Requires-Dist: pickleDB (>=0.9.2,<0.10.0)
